skrooge/__init__.py
skrooge/__main__.py
skrooge/cli.py
skrooge/instances.json
skrooge/render.py
skrooge/scraper.py
skrooge/utils.py
skrooge-1.0.2.dist-info/LICENSE
skrooge-1.0.2.dist-info/METADATA
skrooge-1.0.2.dist-info/WHEEL
skrooge-1.0.2.dist-info/entry_points.txt
skrooge-1.0.2.dist-info/top_level.txt
skrooge-1.0.2.dist-info/RECORD
