Metadata-Version: 2.1
Name: skrooge
Version: 1.0.2
Summary: A quick and dirty kubernetes cost estimator
Author: Michael Warkentin
License: Apache-2.0
Project-URL: Homepage, https://github.com/mwarkentin/skrooge
Project-URL: Changelog, https://github.com/mwarkentin/skrooge/releases
Project-URL: Issues, https://github.com/mwarkentin/skrooge/issues
Project-URL: CI, https://github.com/mwarkentin/skrooge/actions
Classifier: License :: OSI Approved :: Apache Software License
Requires-Python: >=3.8
License-File: LICENSE
Requires-Dist: click
Requires-Dist: click-log
Provides-Extra: lint
Requires-Dist: ruff ; extra == 'lint'
Provides-Extra: scrape
Requires-Dist: pandas ; extra == 'scrape'
Requires-Dist: requests ; extra == 'scrape'
Requires-Dist: lxml ; extra == 'scrape'
Provides-Extra: test
Requires-Dist: pytest ; extra == 'test'
Requires-Dist: pytest-cov ; extra == 'test'
